{
  "dataset": {
    "dataset_dir": "/mnt/data/Documents/surbhi/dataset",
    "num_classes": 24,
    "train_samples": 1947,
    "val_samples": 480,
    "class_labels": [
      "A-samples",
      "B-samples",
      "C-samples",
      "D-samples",
      "E-samples",
      "F-samples",
      "G-samples",
      "H-samples",
      "I-samples",
      "K-samples",
      "L-samples",
      "M-samples",
      "N-samples",
      "O-samples",
      "P-samples",
      "Q-samples",
      "R-samples",
      "S-samples",
      "T-samples",
      "U-samples",
      "V-samples",
      "W-samples",
      "X-samples",
      "Y-samples"
    ],
    "image_size": [
      64,
      64
    ],
    "validation_split": 0.2,
    "class_distribution": {
      "A-samples": 101,
      "B-samples": 101,
      "C-samples": 102,
      "D-samples": 102,
      "E-samples": 101,
      "F-samples": 102,
      "G-samples": 101,
      "H-samples": 102,
      "I-samples": 100,
      "K-samples": 101,
      "L-samples": 100,
      "M-samples": 102,
      "N-samples": 100,
      "O-samples": 100,
      "P-samples": 102,
      "Q-samples": 101,
      "R-samples": 100,
      "S-samples": 99,
      "T-samples": 100,
      "U-samples": 106,
      "V-samples": 102,
      "W-samples": 100,
      "X-samples": 102,
      "Y-samples": 100
    }
  },
  "model": {
    "architecture": "MobileNetV2 (frozen) + Flatten + Dense(128, ReLU) + Dropout(0.5) + Dense(24, Softmax)",
    "base_model": "MobileNetV2 (ImageNet weights, frozen)",
    "input_shape": "(64, 64, 3)",
    "output_shape": "(None, 24)",
    "total_params": 2943768,
    "trainable_params": 2201944,
    "non_trainable_params": 741824,
    "model_path": "/mnt/data/Documents/surbhi/saved_models/sign_model.h5",
    "model_size_mb": 28.45
  },
  "training": {
    "optimizer": "Adam",
    "learning_rate": 0.0005,
    "loss_function": "CategoricalCrossentropy",
    "batch_size": 64,
    "max_epochs": 200,
    "early_stopping_patience": 100,
    "actual_epochs": 200,
    "training_time_sec": 1340.91,
    "final_train_loss": 0.093156,
    "final_train_accuracy": 0.987673,
    "final_val_loss": 0.372729,
    "final_val_accuracy": 0.972917,
    "best_val_loss": 0.083579,
    "best_val_accuracy": 0.9875,
    "best_epoch": 182,
    "loss_per_epoch": [
      3.213283,
      2.02225,
      1.473905,
      1.019493,
      0.784005,
      0.629287,
      0.56561,
      0.469122,
      0.445624,
      0.439324,
      0.407188,
      0.336295,
      0.3909,
      0.300988,
      0.305286,
      0.281567,
      0.251563,
      0.227712,
      0.240996,
      0.197136,
      0.23534,
      0.211842,
      0.195388,
      0.199806,
      0.200481,
      0.204558,
      0.228782,
      0.184528,
      0.191136,
      0.15036,
      0.173338,
      0.197347,
      0.168803,
      0.130376,
      0.113686,
      0.122753,
      0.169642,
      0.17349,
      0.170519,
      0.153022,
      0.133323,
      0.157832,
      0.121452,
      0.198327,
      0.154348,
      0.165309,
      0.149991,
      0.189511,
      0.189657,
      0.178507,
      0.121695,
      0.173979,
      0.159342,
      0.143832,
      0.168031,
      0.151676,
      0.172812,
      0.141532,
      0.159218,
      0.192534,
      0.154734,
      0.130206,
      0.116627,
      0.131752,
      0.102771,
      0.097051,
      0.09662,
      0.122297,
      0.151952,
      0.142821,
      0.15749,
      0.103718,
      0.201923,
      0.132285,
      0.11826,
      0.134633,
      0.170301,
      0.142858,
      0.112426,
      0.108973,
      0.116159,
      0.111376,
      0.115757,
      0.084703,
      0.10158,
      0.105229,
      0.082504,
      0.065583,
      0.090155,
      0.093922,
      0.106118,
      0.083029,
      0.08075,
      0.099501,
      0.11081,
      0.115959,
      0.099221,
      0.067138,
      0.084434,
      0.066512,
      0.099334,
      0.095638,
      0.188398,
      0.127533,
      0.089576,
      0.120732,
      0.135916,
      0.121723,
      0.141469,
      0.097764,
      0.105493,
      0.090547,
      0.142971,
      0.168398,
      0.157486,
      0.097625,
      0.099753,
      0.138768,
      0.138391,
      0.087564,
      0.086106,
      0.116291,
      0.130318,
      0.104177,
      0.101949,
      0.14533,
      0.093374,
      0.128022,
      0.089153,
      0.120047,
      0.132444,
      0.107054,
      0.135962,
      0.08465,
      0.086248,
      0.064083,
      0.080344,
      0.086192,
      0.060687,
      0.067306,
      0.101965,
      0.086915,
      0.080931,
      0.08476,
      0.07639,
      0.070073,
      0.08807,
      0.127478,
      0.097249,
      0.121641,
      0.094529,
      0.082939,
      0.061927,
      0.062903,
      0.094255,
      0.075632,
      0.107385,
      0.127227,
      0.079879,
      0.074684,
      0.120131,
      0.094467,
      0.071469,
      0.094575,
      0.072499,
      0.07049,
      0.083903,
      0.164332,
      0.102579,
      0.073631,
      0.076416,
      0.065249,
      0.103503,
      0.072279,
      0.092776,
      0.118554,
      0.149604,
      0.144327,
      0.116305,
      0.078858,
      0.08721,
      0.083065,
      0.074893,
      0.087209,
      0.071364,
      0.132438,
      0.106495,
      0.115489,
      0.083524,
      0.07325,
      0.09458,
      0.090212,
      0.13986,
      0.086876,
      0.089746,
      0.08006,
      0.09954,
      0.103956,
      0.088849,
      0.093156
    ],
    "val_loss_per_epoch": [
      2.800099,
      2.641855,
      3.031049,
      3.495204,
      3.674096,
      2.894794,
      3.071686,
      2.92133,
      2.461278,
      2.085651,
      2.433544,
      2.732542,
      2.437397,
      2.414278,
      2.664502,
      2.853087,
      3.218064,
      2.204725,
      2.010328,
      2.096723,
      1.318506,
      1.554987,
      2.161234,
      1.761583,
      1.342959,
      1.677061,
      1.439705,
      2.461105,
      1.36933,
      1.31051,
      1.097438,
      1.17401,
      1.192946,
      0.910747,
      0.928626,
      0.638801,
      0.812596,
      0.998762,
      1.497082,
      0.806554,
      0.675688,
      1.267019,
      0.961229,
      2.127049,
      1.201431,
      0.778776,
      0.817582,
      1.07585,
      0.818973,
      0.981899,
      1.000614,
      1.623418,
      0.928526,
      1.627877,
      1.496944,
      0.771944,
      1.305063,
      1.582646,
      1.013452,
      0.76348,
      0.880736,
      1.337442,
      1.004304,
      0.657113,
      0.659802,
      0.560002,
      0.469322,
      0.628633,
      0.649581,
      0.442871,
      0.785134,
      0.777559,
      0.715147,
      0.529587,
      0.427186,
      0.358487,
      0.812667,
      0.614702,
      0.683061,
      0.299999,
      0.595897,
      0.215223,
      0.302557,
      0.235929,
      0.224927,
      0.403683,
      0.250543,
      0.247468,
      0.44531,
      0.343448,
      0.383243,
      0.262159,
      0.555686,
      0.535031,
      0.633624,
      0.675059,
      0.752533,
      0.400999,
      0.599611,
      0.249993,
      0.25576,
      0.536892,
      0.270965,
      0.714688,
      0.6879,
      0.644067,
      0.436056,
      0.295867,
      0.357145,
      0.159234,
      0.154771,
      0.215318,
      0.163027,
      0.257296,
      0.428439,
      0.346954,
      0.584162,
      0.214112,
      0.374769,
      0.548113,
      0.958699,
      1.090143,
      1.13455,
      0.755794,
      0.52075,
      0.765943,
      0.635183,
      0.687447,
      0.589259,
      0.541532,
      0.555848,
      0.390227,
      0.254243,
      0.209836,
      0.245442,
      0.388467,
      0.46046,
      0.218423,
      0.277666,
      0.38092,
      0.295522,
      0.322098,
      0.451154,
      0.228589,
      0.209736,
      0.269045,
      0.277555,
      0.27224,
      0.346793,
      0.26848,
      0.316313,
      0.19228,
      0.131438,
      0.184982,
      0.619076,
      0.396427,
      0.313115,
      0.190719,
      0.125519,
      0.24471,
      0.398974,
      0.317274,
      0.397148,
      0.266025,
      0.097649,
      0.196681,
      0.168923,
      0.403722,
      0.21396,
      0.347766,
      0.313651,
      0.250587,
      0.233667,
      0.129904,
      0.11754,
      0.313168,
      0.212296,
      0.291251,
      0.297783,
      0.10184,
      0.186285,
      0.083579,
      0.363078,
      0.494015,
      0.416819,
      0.263575,
      0.285503,
      0.228331,
      0.274914,
      0.403679,
      0.293383,
      0.533064,
      0.642381,
      0.494361,
      0.36333,
      0.414087,
      0.317426,
      0.459583,
      0.343272,
      0.372729
    ],
    "accuracy_per_epoch": [
      0.166923,
      0.406266,
      0.585003,
      0.708783,
      0.763739,
      0.822804,
      0.851053,
      0.866975,
      0.879815,
      0.877247,
      0.891115,
      0.911659,
      0.911659,
      0.92604,
      0.928608,
      0.931176,
      0.940935,
      0.942989,
      0.941448,
      0.948639,
      0.95018,
      0.947098,
      0.951207,
      0.959425,
      0.952748,
      0.958911,
      0.952748,
      0.957884,
      0.959938,
      0.969183,
      0.959938,
      0.964047,
      0.969697,
      0.96867,
      0.974833,
      0.975347,
      0.966102,
      0.970211,
      0.96302,
      0.972265,
      0.973292,
      0.969697,
      0.978428,
      0.970724,
      0.971751,
      0.973806,
      0.96867,
      0.969183,
      0.964047,
      0.964561,
      0.976888,
      0.971238,
      0.969697,
      0.972265,
      0.968156,
      0.974319,
      0.964561,
      0.969183,
      0.972779,
      0.965588,
      0.976888,
      0.970211,
      0.98151,
      0.974319,
      0.983051,
      0.984592,
      0.984078,
      0.98151,
      0.976888,
      0.971751,
      0.977401,
      0.984078,
      0.971238,
      0.973292,
      0.973292,
      0.977915,
      0.973806,
      0.967129,
      0.98151,
      0.986133,
      0.977915,
      0.984592,
      0.982024,
      0.985105,
      0.983564,
      0.980996,
      0.988187,
      0.993323,
      0.987673,
      0.987673,
      0.985619,
      0.985619,
      0.986133,
      0.989728,
      0.983564,
      0.985105,
      0.982537,
      0.990241,
      0.986133,
      0.991269,
      0.986646,
      0.985105,
      0.970724,
      0.974833,
      0.98716,
      0.983051,
      0.977915,
      0.978428,
      0.976374,
      0.984592,
      0.985619,
      0.986133,
      0.979969,
      0.970724,
      0.975347,
      0.978942,
      0.983564,
      0.971751,
      0.972779,
      0.989214,
      0.989214,
      0.984592,
      0.978428,
      0.982537,
      0.986133,
      0.985105,
      0.984592,
      0.977915,
      0.985105,
      0.984592,
      0.975347,
      0.983564,
      0.977401,
      0.98716,
      0.985105,
      0.992809,
      0.988187,
      0.991269,
      0.990755,
      0.992809,
      0.989214,
      0.989728,
      0.989728,
      0.98716,
      0.987673,
      0.989214,
      0.990241,
      0.984078,
      0.985105,
      0.983564,
      0.98716,
      0.988187,
      0.992296,
      0.992809,
      0.985619,
      0.988701,
      0.98716,
      0.982537,
      0.990241,
      0.989728,
      0.984078,
      0.986646,
      0.990241,
      0.98716,
      0.989214,
      0.991782,
      0.986133,
      0.983051,
      0.985105,
      0.988701,
      0.991269,
      0.991269,
      0.984078,
      0.986646,
      0.991269,
      0.984078,
      0.980483,
      0.977401,
      0.980483,
      0.98716,
      0.988187,
      0.984592,
      0.988701,
      0.988701,
      0.991782,
      0.984078,
      0.986133,
      0.979456,
      0.988701,
      0.991782,
      0.986646,
      0.988701,
      0.975347,
      0.985105,
      0.987673,
      0.98716,
      0.985105,
      0.98716,
      0.989214,
      0.987673
    ],
    "val_accuracy_per_epoch": [
      0.26875,
      0.416667,
      0.439583,
      0.445833,
      0.475,
      0.46875,
      0.533333,
      0.53125,
      0.59375,
      0.66875,
      0.61875,
      0.645833,
      0.670833,
      0.602083,
      0.622917,
      0.6375,
      0.608333,
      0.683333,
      0.6875,
      0.73125,
      0.770833,
      0.764583,
      0.722917,
      0.75625,
      0.779167,
      0.752083,
      0.775,
      0.708333,
      0.845833,
      0.81875,
      0.852083,
      0.86875,
      0.872917,
      0.88125,
      0.883333,
      0.914583,
      0.864583,
      0.860417,
      0.8375,
      0.895833,
      0.897917,
      0.885417,
      0.908333,
      0.833333,
      0.845833,
      0.922917,
      0.922917,
      0.8875,
      0.897917,
      0.895833,
      0.89375,
      0.872917,
      0.908333,
      0.860417,
      0.864583,
      0.920833,
      0.897917,
      0.885417,
      0.89375,
      0.879167,
      0.854167,
      0.841667,
      0.852083,
      0.89375,
      0.9,
      0.920833,
      0.939583,
      0.916667,
      0.914583,
      0.939583,
      0.90625,
      0.920833,
      0.920833,
      0.94375,
      0.94375,
      0.958333,
      0.9,
      0.933333,
      0.91875,
      0.954167,
      0.939583,
      0.9625,
      0.95625,
      0.9875,
      0.970833,
      0.9625,
      0.979167,
      0.979167,
      0.970833,
      0.958333,
      0.954167,
      0.966667,
      0.941667,
      0.941667,
      0.933333,
      0.922917,
      0.9375,
      0.95625,
      0.935417,
      0.9625,
      0.960417,
      0.922917,
      0.964583,
      0.927083,
      0.9375,
      0.935417,
      0.95,
      0.983333,
      0.95,
      0.966667,
      0.966667,
      0.964583,
      0.964583,
      0.9625,
      0.94375,
      0.95,
      0.94375,
      0.972917,
      0.960417,
      0.95,
      0.933333,
      0.93125,
      0.916667,
      0.952083,
      0.933333,
      0.925,
      0.941667,
      0.902083,
      0.9375,
      0.929167,
      0.933333,
      0.947917,
      0.960417,
      0.9625,
      0.964583,
      0.954167,
      0.9375,
      0.960417,
      0.970833,
      0.966667,
      0.954167,
      0.95625,
      0.941667,
      0.960417,
      0.95625,
      0.9625,
      0.966667,
      0.94375,
      0.952083,
      0.958333,
      0.9625,
      0.975,
      0.972917,
      0.970833,
      0.945833,
      0.95625,
      0.9625,
      0.972917,
      0.970833,
      0.966667,
      0.95,
      0.95625,
      0.95625,
      0.964583,
      0.985417,
      0.964583,
      0.979167,
      0.952083,
      0.972917,
      0.970833,
      0.964583,
      0.964583,
      0.972917,
      0.975,
      0.977083,
      0.94375,
      0.95,
      0.954167,
      0.95625,
      0.985417,
      0.952083,
      0.98125,
      0.9625,
      0.958333,
      0.954167,
      0.954167,
      0.95625,
      0.95,
      0.964583,
      0.952083,
      0.972917,
      0.933333,
      0.925,
      0.941667,
      0.95625,
      0.966667,
      0.954167,
      0.935417,
      0.958333,
      0.972917
    ]
  },
  "evaluation": {
    "accuracy": 0.9729166666666667,
    "precision": 0.977193700019787,
    "recall": 0.9729166666666667,
    "f1_score": 0.9724031464633118,
    "classification_report": "              precision    recall  f1-score   support\n\n   A-samples       1.00      1.00      1.00        20\n   B-samples       1.00      1.00      1.00        20\n   C-samples       1.00      1.00      1.00        20\n   D-samples       0.91      1.00      0.95        20\n   E-samples       1.00      1.00      1.00        20\n   F-samples       0.77      1.00      0.87        20\n   G-samples       1.00      0.95      0.97        20\n   H-samples       0.95      1.00      0.98        20\n   I-samples       1.00      1.00      1.00        20\n   K-samples       1.00      1.00      1.00        20\n   L-samples       1.00      1.00      1.00        20\n   M-samples       0.87      1.00      0.93        20\n   N-samples       0.95      1.00      0.98        20\n   O-samples       1.00      1.00      1.00        20\n   P-samples       1.00      1.00      1.00        20\n   Q-samples       1.00      1.00      1.00        20\n   R-samples       1.00      1.00      1.00        20\n   S-samples       1.00      1.00      1.00        19\n   T-samples       1.00      0.80      0.89        20\n   U-samples       1.00      0.90      0.95        21\n   V-samples       1.00      1.00      1.00        20\n   W-samples       1.00      0.70      0.82        20\n   X-samples       1.00      1.00      1.00        20\n   Y-samples       1.00      1.00      1.00        20\n\n    accuracy                           0.97       480\n   macro avg       0.98      0.97      0.97       480\nweighted avg       0.98      0.97      0.97       480\n"
  },
  "inference": {
    "rama.webm": {
      "final_decoded": "X-samples-samples-samples-samples-samples-samples-samples",
      "video_path": "/mnt/data/Documents/surbhi/video/rama.webm"
    },
    "signv.mp4": {
      "final_decoded": "F-samples-samples-samples-samples-samples-samples",
      "video_path": "/mnt/data/Documents/surbhi/video/signv.mp4"
    }
  },
  "tflite": {
    "tflite_path": "/mnt/data/Documents/surbhi/saved_models/sign_model.tflite",
    "tflite_size_mb": 3.03,
    "quantization": "tf.lite.Optimize.DEFAULT"
  }
}